Workbook

Sheet Paramètres
A1: Paramètres du score d'opportunité territoriale
A2: Les 4 pondérations ci-dessous pilotent la colonne SCORE de l'onglet « 59 bassins ». Modifiez-les pour tester une autre hypothèse de priorisation.
A4: Axe du score | B4: Pondération | C4: Nature de la donnée sous-jacente
A5: Vivier B1 compatible | B5: 0.4 | C5: PROXY — population INSEE × 1,05 % (ratio national Terminale). Pas un effectif observé.
A6: Affinité avec les filières NEXA | B6: 0.25 | C6: ESTIMATION EXPERTE — déduite du tissu économique. PAS une donnée DEPP.
A7: Concentration géographique du vivier | B7: 0.2 | C7: OBSERVÉ — calcul sur données INSEE/La Poste.
A8: Potentiel économique numérique | B8: 0.15 | C8: ESTIMATION EXPERTE — ancrée sur labels French Tech et grands employeurs.
A9: Total (doit valoir 100 %) | B9: =SUM(B5:B8) -> 1 | C9: =IF(ABS(B9-1)<0.0001,"OK","ERREUR : la somme des pondérations doit faire 100 %") -> OK
A11: Ce qui n'entre volontairement PAS dans le score
A12: Conformément au cadre de mission, aucune variable de « propension au distanciel » n'est intégrée : éloignement d'une université, absence d'école numérique, ruralité, présence d'un Campus connecté, coût du logement étudiant, densité d'enseignement supérieur, IPS, profil socio-économique. Ces variables sont collectées séparément (onglet « Hypothèses H1-H8 ») pour être confrontées aux résultats commerciaux réels de l'année 1.
A13: Le coût de déplacement n'entre pas davantage dans le score ni dans la sélection des zones. La distance aux campus est publiée à titre d'information de planification uniquement.
A14: Conséquence assumée : les 12 zones P1 contiennent toutes un pôle étudiant majeur. Le score, ne récompensant que le vivier, l'affinité, la concentration et l'économie, désigne mécaniquement des territoires bien dotés — l'inverse de l'intuition du « territoire idéal pour le distanciel ». C'est pourquoi le portefeuille de test ne se limite pas aux P1.

Sheet Synthèse
A1: NEXA À distance — Où tester les Interventions Extérieures ?
A2: Étape 1 : livrable territorial. Aucune liste de lycées à ce stade (objet de l'étape 2). Production : 15 août 2026.
A4: Indicateur | B4: Valeur | C4: Nature
A5: Communes analysées | B5: 34 863 (68,3 M hab.) | C5: observé — INSEE / Etalab
A6: Communes exclues (≤ 60 km de Paris, Lyon ou Lille) | B6: 2 982 (19,1 M hab. — 28,0 %) | C6: calculé — distance orthodromique, commune par commune
A7: Départements totalement exclus | B7: 4 (75, 92, 93, 94) | C7: calculé
A8: Départements partiellement touchés, restant exploitables | B8: 11 | C8: calculé — aucun département exclu en bloc
A9: Bassins d'opportunité construits | B9: 75 | C9: calculé — algorithme glouton, rayon 30 km
A10: Bassins retenus et scorés | B10: 59 | C10: ≥ 250 000 hab. + 5 villes moyennes ajoutées pour tester H7
A11: Répartition des priorités | B11: 12 P1 · 18 P2 · 29 P3/TEST | C11: calculé
A12: Zones recommandées au test année 1 | B12: 9 | C12: 6 cœur de cible · 2 adjacentes · 1 expérimentale
A15: Les trois questions auxquelles ce classeur répond
A16: 1. OÙ tester ? → onglets « Portefeuille test » (les 9 zones) et « 59 bassins » (l'univers complet).
A17: 2. POURQUOI ces zones plutôt que d'autres ? → colonne « Pourquoi » de l'onglet « 59 bassins », onglet « Fiches P1 », et ANNEXE A (démarche).
A18: 3. QU'ALLONS-NOUS APPRENDRE ? → onglet « Hypothèses H1-H8 » et onglets « Sans pôle étudiant » / « Anomalies ».
A20: Deux avertissements à lire avant d'engager un budget
A21: ① L'axe « affinité filières » n'est PAS une donnée de l'Éducation nationale. L'accès réseau à data.education.gouv.fr était bloqué pendant la production : les effectifs réels par établissement, série et spécialité (NSI, STI2D, CIEL, STMG) n'ont pas pu être téléchargés. Le vivier est un PROXY (population × 1,05 %) et les potentiels par filière des ESTIMATIONS EXPERTES fondées sur le tissu économique. Un script prêt à l'emploi (pipeline/05_enrichissement_depp.py) remplace ces colonnes par les données observées dès qu'il est lancé depuis un poste au réseau ouvert. C'est la première action à mener.
A22: ② Le classement P1/P2/P3 doit être considéré comme provisoire tant que cette collecte n'a pas eu lieu : 40 % du score repose sur un proxy et 40 % sur du jugement expert. Seuls 20 % (la concentration) sont entièrement observés. Les écarts de score inférieurs à ~5 points ne sont pas significatifs.
A24: Recommandation
A25: Tester 9 bassins, pas 59. La contrainte réelle n'est pas le nombre de zones intéressantes — il y en a beaucoup — mais le nombre d'IE nécessaires pour qu'une zone produise un signal lisible. En dessous de 3 à 5 IE dans un bassin, un résultat nul ne se distingue pas du bruit : on ne saura pas si la zone est mauvaise ou si elle a été mal travaillée. Sur une saison (octobre → mars, ~20 semaines utiles) : 9 bassins × 4 à 5 IE ≈ 40 IE.
A26: Si la capacité de l'équipe est inférieure, réduire le NOMBRE DE ZONES, pas le nombre d'IE par zone. Liste courte à 5 zones : Marseille, Toulouse, Rennes, Niort, Béziers.

Sheet Portefeuille test
A1: Portefeuille de test recommandé — 9 bassins
A2: Logique 70 / 20 / 10. Sélection fondée sur les fondamentaux et la diversité des profils : le coût de déplacement n'intervient pas.
A4: Rôle | B4: Bassin | C4: Rang | D4: Vivier B1 (Tle est.) | E4: Profil dominant | F4: Ce que cette zone apporte au panel | G4: Hypothèse principale testée
A5: Cœur de cible | B5: Marseille – Aix | C5: 1 | D5: 18520 | E5: Cyber + Dev + Data/IA | F5: Le plus gros vivier de France hors exclusion (+33 % sur Toulouse). Mesure le plafond de ce qu'une zone peut produire. | G5: H3 — économie numérique
A6: Cœur de cible | B6: Toulouse | C6: 2 | D6: 13900 | E6: Cyber + Dev + Data/IA | F6: Affinité maximale du panel (94/100) ET forte concentration (81/100). Aéronautique, spatial, embarqué. | G6: H5 — NSI / STI2D → Cyber-Dev
A7: Cœur de cible | B7: Bordeaux | C7: 3 | D7: 12650 | E7: Dev + Marketing | F7: Le seul gros vivier du cœur orienté marketing (Cdiscount, Ubisoft, vin, tourisme) — famille que Toulouse, Rennes et Grenoble couvrent mal. | G7: H6 — STMG → Marketing Digital
A8: Cœur de cible | B8: Rennes | C8: 6 | D8: 7500 | E8: Cyber pur | F8: Pôle cyber national (COMCYBER, DGA-MI). Bassin le plus compact du top 10 (87/100). À opposer directement à Vannes. | G8: H1 (contre-test) — offre locale forte
A9: Cœur de cible | B9: Grenoble | C9: 7 | D9: 7210 | E9: Cyber + Dev + Data/IA | F9: Territoire délibérément spécialisé (marketing 3/5) : permet de tester l'offre technique isolément. Concentration maximale du panel (88/100). | G9: H5 — vivier scientifique
A10: Cœur de cible | B10: Rouen | C10: 11 | D10: 8080 | E10: Cyber industriel | F10: Seul profil non « French Tech » du cœur (économie 3/5) : chimie, port, logistique, assurance. Gros vivier (6e du panel). | G10: H4 — alternance vs recrutement
A11: Cible adjacente | B11: Niort | C11: 27 | D11: 2390 | E11: Dev + Data/IA | F11: L'anomalie la plus forte du panel : affinité 88/100 pour un vivier indexé à 1/100 (MAIF, MACIF, MAAF, Groupama). L'affinité compense-t-elle le volume ? | G11: H7 — villes moyennes
A12: Cible adjacente | B12: Vannes | C12: 19 | D12: 3460 | E12: Cyber | F12: Pôle cyber breton SANS université de plein exercice (pôle étudiant à 47 km). Même filière que Rennes, configuration inverse. | G12: H1 + H2 — faible offre locale
A13: Zone expérimentale | B13: Béziers – Narbonne | C13: 55 | D13: 4410 | E13: Marketing | F13: Le contre-test le plus pur : vivier réel supérieur à Niort et Vannes, mais économie numérique 1/5 et aucun pôle étudiant à moins de 59 km. | G13: H1 + H3 — contre-test
A15: TOTAL vivier estimé du portefeuille | D15: =SUM(D5:D13) -> 78120 | F15: ="soit environ "&TEXT(D15/SUM('59 bassins'!H2:H60),"0.0%")&" du vivier estimé des 59 bassins de l'univers" -> soit environ 25.3% du vivier estimé des 59 bassins de l'univers
A17: Réserves immédiates
A18: Nantes (4e) et Nice (5e) sont volontairement écartés du premier lot — non par manque de potentiel, mais parce que leurs profils recoupent presque exactement ceux de Bordeaux et de Toulouse. Retenir les six premiers du classement reviendrait à tester trois configurations en en payant six. À substituer immédiatement si une zone du cœur se révèle inexploitable.
A20: Le cas à part : La Réunion
A21: La Réunion (17e, ~7 120 Terminales estimées) est le test le plus discriminant de H2 — éloignement maximal de toute alternative métropolitaine. Elle n'est pas dans les 9 pour son potentiel, mais parce qu'elle appelle une modalité de test différente : webinaires, partenariats rectorat et lycées, relais locaux, plutôt que des IE en présentiel. À lancer en parallèle, sur un budget distinct.
A23: Si la capacité ne permet que 5 bassins
A24: Marseille, Toulouse, Rennes, Niort, Béziers. On garde les deux plus gros viviers, un profil cyber très concentré, l'anomalie d'affinité et le contre-test — c'est-à-dire l'essentiel du pouvoir d'apprentissage du panel complet.

Sheet 59 bassins
A1: Rang | B1: Bassin | C1: Priorité | D1: Région(s) | E1: Départements | F1: Villes principales | G1: Population du bassin | H1: Vivier B1 Terminales estimées (PROXY) | I1: Nb communes | J1: Nb villes ≥ 10 000 hab. | K1: Étendue du bassin (km) | L1: Population à ≤ 20 km (%) | M1: Cyber (1-5) | N1: Dev (1-5) | O1: Data/IA (1-5) | P1: Marketing (1-5) | Q1: Filières dominantes | R1: Économie numérique (1-5) | S1: Sous-score vivier /100 | T1: Sous-score affinité /100 | U1: Sous-score concentration /100 | V1: Sous-score économie /100 | W1: SCORE | X1: Pôle étudiant majeur dans le bassin | Y1: Distance au pôle étudiant (km) | Z1: Distance au campus NEXA (km) | AA1: Campus le plus proche | AB1: Pourquoi cette zone mérite notre attention
A2: =RANK(W2,$W$2:$W$60) -> 1 | B2: Marseille | C2: =IF(A2<=12,"P1",IF(A2<=30,"P2","P3/TEST")) -> P1 | D2: Provence-Alpes-Côte d'Azur | E2: 13 Bouches-du-Rhône | F2: Marseille (886k), Aix-en-Provence (150k), Martigues (48k), Aubagne (48k), Istres (44k) | G2: 1764141 | H2: 18520 | I2: 69 | J2: 25 | K2: 57.1 | L2: 80.4 | M2: 5 | N2: 5 | O2: 5 | P2: 4 | Q2: Cyber+Dev+Data/IA | R2: 5 | S2: 100 | T2: 93.75 | U2: 60.06 | V2: 100 | W2: =ROUND(Paramètres!$B$5*S2+Paramètres!$B$6*T2+Paramètres!$B$7*U2+Paramètres!$B$8*V2,1) -> 90.4 | X2: oui | Y2: 3 | Z2: 276.6 | AA2: Lyon | AB2: 2e ville de France ; 4e hub internet europeen (cables sous-marins, data centers), CMA CGM, STMicroelectronics Rousset, Airbus Helicopters ; Aix-Marseille Universite
A3: =RANK(W3,$W$2:$W$60) -> 2 | B3: Toulouse | C3: =IF(A3<=12,"P1",IF(A3<=30,"P2","P3/TEST")) -> P1 | D3: Occitanie | E3: 31 Haute-Garonne, 32 Gers, 81 Tarn | F3: Toulouse (515k), Colomiers (41k), Tournefeuille (30k), Blagnac (28k), Muret (26k) | G3: 1323768 | H3: 13900 | I3: 232 | J3: 18 | K3: 38.5 | L3: 85.4 | M3: 5 | N3: 5 | O3: 5 | P3: 4 | Q3: Cyber+Dev+Data/IA | R3: 5 | S3: 79.408897 | T3: 93.75 | U3: 80.66 | V3: 100 | W3: =ROUND(Paramètres!$B$5*S3+Paramètres!$B$6*T3+Paramètres!$B$7*U3+Paramètres!$B$8*V3,1) -> 86.3 | X3: oui | Y3: 1.4 | Z3: 360.6 | AA3: Lyon | AB3: Aeronautique-spatial (Airbus, Thales, CNES), 1er bassin d'emploi ingenieur hors IDF
A4: =RANK(W4,$W$2:$W$60) -> 3 | B4: Bordeaux | C4: =IF(A4<=12,"P1",IF(A4<=30,"P2","P3/TEST")) -> P1 | D4: Nouvelle-Aquitaine | E4: 33 Gironde | F4: Bordeaux (268k), Mérignac (78k), Pessac (67k), Talence (46k), Villenave-d'Ornon (43k) | G4: 1204696 | H4: 12650 | I4: 176 | J4: 24 | K4: 44 | L4: 82.1 | M4: 4 | N4: 5 | O4: 4 | P4: 5 | Q4: Dev+Marketing | R4: 5 | S4: 73.266592 | T4: 87.5 | U4: 73.84 | V4: 100 | W4: =ROUND(Paramètres!$B$5*S4+Paramètres!$B$6*T4+Paramètres!$B$7*U4+Paramètres!$B$8*V4,1) -> 80.9 | X4: oui | Y4: 2.3 | Z4: 434.3 | AA4: Lyon | AB4: Capitale French Tech ; Cdiscount, Ubisoft, aeronautique-defense-spatial (Dassault, Thales, ArianeGroup) ; vin et tourisme = fort vivier marketing
A5: =RANK(W5,$W$2:$W$60) -> 4 | B5: Nantes | C5: =IF(A5<=12,"P1",IF(A5<=30,"P2","P3/TEST")) -> P1 | D5: Pays de la Loire | E5: 44 Loire-Atlantique, 85 Vendée | F5: Nantes (328k), Saint-Herblain (51k), Rezé (44k), Saint-Sébastien-sur-Loire (29k), Orvault (29k) | G5: 989985 | H5: 10390 | I5: 94 | J5: 14 | K5: 39.4 | L5: 79.9 | M5: 4 | N5: 5 | O5: 4 | P5: 5 | Q5: Dev+Marketing | R5: 5 | S5: 61.334279 | T5: 87.5 | U5: 77.56 | V5: 100 | W5: =ROUND(Paramètres!$B$5*S5+Paramètres!$B$6*T5+Paramètres!$B$7*U5+Paramètres!$B$8*V5,1) -> 76.9 | X5: oui | Y5: 1.6 | Z5: 343.1 | AA5: Paris | AB5: Capitale French Tech, Atlanpole et quartier de la creation ; Airbus, forte densite d'ESN ; premier ecosysteme numerique de l'Ouest
A6: =RANK(W6,$W$2:$W$60) -> 5 | B6: Nice | C6: =IF(A6<=12,"P1",IF(A6<=30,"P2","P3/TEST")) -> P1 | D6: Provence-Alpes-Côte d'Azur | E6: 06 Alpes-Maritimes, 83 Var | F6: Nice (358k), Antibes (78k), Cannes (74k), Fréjus (60k), Cagnes-sur-Mer (53k) | G6: 1093251 | H6: 11480 | I6: 87 | J6: 18 | K6: 47.6 | L6: 51 | M6: 5 | N6: 5 | O6: 4 | P6: 4 | Q6: Cyber+Dev | R6: 5 | S6: 67.235886 | T6: 87.5 | U6: 57.8 | V6: 100 | W6: =ROUND(Paramètres!$B$5*S6+Paramètres!$B$6*T6+Paramètres!$B$7*U6+Paramètres!$B$8*V6,1) -> 75.3 | X6: oui | Y6: 2 | Z6: 296.4 | AA6: Lyon | AB6: Sophia Antipolis, 1er technopole europeen ; Amadeus, Orange Labs ; economie touristique = vivier marketing
A7: =RANK(W7,$W$2:$W$60) -> 6 | B7: Rennes | C7: =IF(A7<=12,"P1",IF(A7<=30,"P2","P3/TEST")) -> P1 | D7: Bretagne | E7: 35 Ille-et-Vilaine | F7: Rennes (231k), Bruz (20k), Cesson-Sévigné (19k), Saint-Jacques-de-la-Lande (14k), Betton (13k) | G7: 714155 | H7: 7500 | I7: 144 | J7: 8 | K7: 22.3 | L7: 79.8 | M7: 5 | N7: 5 | O7: 4 | P7: 4 | Q7: Cyber+Dev | R7: 5 | S7: 43.981997 | T7: 87.5 | U7: 86.92 | V7: 100 | W7: =ROUND(Paramètres!$B$5*S7+Paramètres!$B$6*T7+Paramètres!$B$7*U7+Paramètres!$B$8*V7,1) -> 71.9 | X7: oui | Y7: 0.7 | Z7: 309.9 | AA7: Paris | AB7: Pole cyber national (COMCYBER, DGA-MI, campus cyber breton), b<>com, telecoms
A8: =RANK(W8,$W$2:$W$60) -> 7 | B8: Grenoble | C8: =IF(A8<=12,"P1",IF(A8<=30,"P2","P3/TEST")) -> P1 | D8: Auvergne-Rhône-Alpes | E8: 38 Isère | F8: Grenoble (156k), Saint-Martin-d'Hères (38k), Échirolles (37k), Fontaine (22k), Voiron (22k) | G8: 686820 | H8: 7210 | I8: 181 | J8: 11 | K8: 29.4 | L8: 81.7 | M8: 5 | N8: 5 | O8: 5 | P8: 3 | Q8: Cyber+Dev+Data/IA | R8: 5 | S8: 42.067979 | T8: 87.5 | U8: 88.28 | V8: 100 | W8: =ROUND(Paramètres!$B$5*S8+Paramètres!$B$6*T8+Paramètres!$B$7*U8+Paramètres!$B$8*V8,1) -> 71.4 | X8: oui | Y8: 0.8 | Z8: 94.3 | AA8: Lyon | AB8: Microelectronique CEA-Leti, STMicroelectronics ; hub deeptech de rang mondial
A9: =RANK(W9,$W$2:$W$60) -> 8 | B9: Strasbourg | C9: =IF(A9<=12,"P1",IF(A9<=30,"P2","P3/TEST")) -> P1 | D9: Grand Est | E9: 67 Bas-Rhin | F9: Strasbourg (294k), Haguenau (36k), Schiltigheim (35k), Illkirch-Graffenstaden (28k), Lingolsheim (21k) | G9: 852523 | H9: 8950 | I9: 204 | J9: 12 | K9: 48.5 | L9: 75.7 | M9: 4 | N9: 4 | O9: 4 | P9: 4 | Q9: Cyber+Dev+Data/IA+Marketing | R9: 4 | S9: 53.040184 | T9: 75 | U9: 66.78 | V9: 75 | W9: =ROUND(Paramètres!$B$5*S9+Paramètres!$B$6*T9+Paramètres!$B$7*U9+Paramètres!$B$8*V9,1) -> 64.6 | X9: oui | Y9: 1.2 | Z9: 383.5 | AA9: Lyon | AB9: Capitale europeenne, banque-assurance, industrie ; ecosysteme numerique structure
A10: =RANK(W10,$W$2:$W$60) -> 9 | B10: Montpellier | C10: =IF(A10<=12,"P1",IF(A10<=30,"P2","P3/TEST")) -> P1 | D10: Occitanie | E10: 34 Hérault, 30 Gard | F10: Montpellier (310k), Nîmes (152k), Lunel (27k), Castelnau-le-Lez (26k), Lattes (17k) | G10: 960447 | H10: 10080 | I10: 136 | J10: 12 | K10: 53 | L10: 32.8 | M10: 4 | N10: 5 | O10: 4 | P10: 4 | Q10: Dev | R10: 4 | S10: 59.599883 | T10: 81.25 | U10: 45.12 | V10: 75 | W10: =ROUND(Paramètres!$B$5*S10+Paramètres!$B$6*T10+Paramètres!$B$7*U10+Paramètres!$B$8*V10,1) -> 64.4 | X10: oui | Y10: 0.7 | Z10: 250.3 | AA10: Lyon | AB10: IBM, Dell, sante-numerique ; corridor Montpellier-Nimes tres dynamique demographiquement
A11: =RANK(W11,$W$2:$W$60) -> 10 | B11: Angers | C11: =IF(A11<=12,"P1",IF(A11<=30,"P2","P3/TEST")) -> P1 | D11: Pays de la Loire | E11: 49 Maine-et-Loire | F11: Angers (159k), Mauges-sur-Loire (19k), Loire-Authion (17k), Trélazé (16k), Avrillé (15k) | G11: 483174 | H11: 5070 | I11: 87 | J11: 7 | K11: 33.9 | L11: 72 | M11: 4 | N11: 5 | O11: 4 | P11: 4 | Q11: Dev | R11: 4 | S11: 26.550701 | T11: 81.25 | U11: 72.4 | V11: 75 | W11: =ROUND(Paramètres!$B$5*S11+Paramètres!$B$6*T11+Paramètres!$B$7*U11+Paramètres!$B$8*V11,1) -> 56.7 | X11: oui | Y11: 2 | Z11: 264.7 | AA11: Paris | AB11: Capitale French Tech, Cite de l'objet connecte, electronique-IoT, Thales
A12: =RANK(W12,$W$2:$W$60) -> 11 | B12: Rouen | C12: =IF(A12<=12,"P1",IF(A12<=30,"P2","P3/TEST")) -> P1 | D12: Normandie | E12: 76 Seine-Maritime, 27 Eure | F12: Rouen (118k), Saint-Étienne-du-Rouvray (30k), Sotteville-lès-Rouen (29k), Le Grand-Quevilly (26k), Le Petit-Quevilly (22k) | G12: 769914 | H12: 8080 | I12: 336 | J12: 16 | K12: 42.3 | L12: 77.8 | M12: 4 | N12: 3 | O12: 3 | P12: 3 | Q12: Cyber | R12: 3 | S12: 47.702081 | T12: 56.25 | U12: 73.82 | V12: 50 | W12: =ROUND(Paramètres!$B$5*S12+Paramètres!$B$6*T12+Paramètres!$B$7*U12+Paramètres!$B$8*V12,1) -> 55.4 | X12: oui | Y12: 0.5 | Z12: 112.1 | AA12: Paris | AB12: Chimie-industrie-logistique portuaire, assurance (Matmut) ; besoins IT industriels
A13: =RANK(W13,$W$2:$W$60) -> 12 | B13: Clermont-Ferrand | C13: =IF(A13<=12,"P1",IF(A13<=30,"P2","P3/TEST")) -> P1 | D13: Auvergne-Rhône-Alpes | E13: 63 Puy-de-Dôme | F13: Clermont-Ferrand (146k), Cournon-d'Auvergne (20k), Riom (19k), Chamalières (18k), Issoire (15k) | G13: 529942 | H13: 5560 | I13: 208 | J13: 9 | K13: 41.3 | L13: 77.4 | M13: 4 | N13: 4 | O13: 4 | P13: 3 | Q13: Cyber+Dev+Data/IA | R13: 4 | S13: 30.355906 | T13: 68.75 | U13: 72.16 | V13: 75 | W13: =ROUND(Paramètres!$B$5*S13+Paramètres!$B$6*T13+Paramètres!$B$7*U13+Paramètres!$B$8*V13,1) -> 55 | X13: oui | Y13: 2.4 | Z13: 133.2 | AA13: Lyon | AB13: Michelin (data/IA industrielle), Limagrain ; universite scientifique
... A60: =RANK(W60,$W$2:$W$60) -> 59 | B60: Saint-Quentin | C60: =IF(A60<=12,"P1",IF(A60<=30,"P2","P3/TEST")) -> P3/TEST | D60: Hauts-de-France | E60: 02 Aisne, 80 Somme, 59 Nord, 60 Oise | F60: Saint-Quentin (53k), Tergnier (13k), Péronne (7k), Bohain-en-Vermandois (6k), Gauchy (5k) | G60: 252540 | H60: 2650 | I60: 346 | J60: 2 | K60: 25.4 | L60: 53.3 | M60: 2 | N60: 2 | O60: 2 | P60: 3 | Q60: Marketing | R60: 1 | S60: 4.2210247 | T60: 31.25 | U60: 60.92 | V60: 0 | W60: =ROUND(Paramètres!$B$5*S60+Paramètres!$B$6*T60+Paramètres!$B$7*U60+Paramètres!$B$8*V60,1) -> 21.7 | X60: non | Y60: 56.7 | Z60: 85.2 | AA60: Lille | AB60: Industrie en reconversion ; economie numerique tres faible

Sheet Fiches P1
A1: Lecture stratégique des 12 zones P1
A2: Le coût de déplacement n'intervient dans aucune de ces recommandations : les zones sont jugées sur leurs fondamentaux.
A4: Rang | B4: Bassin | C4: Pourquoi il ressort | D4: Vivier | E4: Affinité NEXA | F4: Concentration | G4: Économie numérique | H4: Hypothèses à tester | I4: Limites / vigilance | J4: Recommandation
A5: 1 | B5: Marseille – Aix | C5: Le premier vivier de France hors exclusion, et de très loin : ~18 520 Terminales estimées, soit 33 % de plus que Toulouse. 2e ville de France, 1re université de France par les effectifs. | D5: 1 764 141 hab. · 69 communes · 25 villes ≥ 10 000 hab. — le plus grand nombre de points d'appui IE du panel. | E5: Cyber 5 · Dev 5 · Data/IA 5 · Mkt 4. 4e hub internet européen (câbles sous-marins, data centers), CMA CGM, STMicroelectronics Rousset, Airbus Helicopters. | F5: 60/100. 80 % de la population à ≤ 20 km mais étendue de 57 km : bassin tricéphale (Marseille / Aix / étang de Berre). | G5: 5/5. Potentiel d'alternance considérable sur les quatre familles. | H5: H3, H5. Sert de plafond de référence. | I5: Forte hétérogénéité sociale : Marseille Nord, Marseille Sud et Aix sont trois marchés très différents, que le vivier proxy ne capte pas. | J5: P1 — retenu au portefeuille, avec un plan de tournée en trois sous-ensembles.
A6: 2 | B6: Toulouse | C6: 2e vivier de l'univers (~13 900 Tle est.), affinité la plus élevée du panel (94/100) et très bonne concentration. | D6: 1 323 768 hab. · 232 communes · 18 villes ≥ 10 000 hab. · étendue 38,5 km. | E6: Cyber 5 · Dev 5 · Data/IA 5 · Mkt 4. Aéronautique et spatial (Airbus, Thales Alenia Space, CNES), 1er bassin d'emploi ingénieur hors IDF. | F6: 81/100, excellente. 85 % de la population à ≤ 20 km. | G6: 5/5. | H6: H3, H5. | I6: Zone la plus concurrentielle de France sur les formations numériques privées : une part du vivier est déjà couverte en présentiel. Le score, qui ne mesure pas la propension au distanciel, peut surestimer le potentiel réel. | J6: P1 — retenu au portefeuille.
A7: 3 | B7: Bordeaux | C7: 3e vivier de l'univers (~12 650 Tle est.), Capitale French Tech, concentration remarquable pour cette taille (24 villes ≥ 10 000 hab. dans 44 km). | D7: 1 204 696 hab. · 176 communes. | E7: Cyber 4 · Dev 5 · Data/IA 4 · Mkt 5. Profil rare : Cdiscount, Ubisoft, aéronautique-défense-spatial (Dassault, Thales, ArianeGroup), économie du vin et du tourisme. | F7: 74/100. 82 % de la population à ≤ 20 km. | G7: 5/5. | H7: H6 en priorité (Marketing Digital sur gros vivier). | I7: Offre supérieure locale très dense : comme à Toulouse, une part du vivier est déjà captée en présentiel. | J7: P1 — retenu au portefeuille : seul gros vivier du cœur orienté Marketing.
A8: 4 | B8: Nantes | C8: ~10 390 Tle est., bonne concentration (78/100) et l'un des écosystèmes numériques les plus dynamiques de France. | D8: 989 985 hab. · 94 communes · 14 villes ≥ 10 000 hab. | E8: Cyber 4 · Dev 5 · Data/IA 4 · Mkt 5. Capitale French Tech, Atlanpole, quartier de la création, Airbus, forte densité d'ESN. | F8: 78/100, très bonne. | G8: 5/5. | H8: H6, H3. | I8: Profil recoupant très largement celui de Bordeaux : les tester tous deux la même année apporterait peu d'information supplémentaire. Saint-Nazaire et Cholet sont limitrophes. | J8: P1 — 1re réserve du portefeuille.
A9: 5 | B9: Nice – Antibes – Cannes | C9: ~11 480 Tle est. adossées à Sophia Antipolis, 1er technopôle européen. Volume métropolitain ET spécialisation numérique forte. | D9: 1 093 251 hab. · 87 communes · 18 villes ≥ 10 000 hab. | E9: Cyber 5 · Dev 5 · Data/IA 4 · Mkt 4. Sophia Antipolis (Amadeus, Orange Labs), économie touristique et évènementielle haut de gamme. | F9: 58/100, la plus faible du top 5. Bassin LINÉAIRE : 47,6 km d'étendue, 51 % de la population à ≤ 20 km. | G9: 5/5. | H9: H3, H5, H6. | I9: La linéarité impose une tournée en axe, pas en étoile. Le profil cyber/dev recoupe Marseille et Toulouse. | J9: P1 — 2e réserve du portefeuille.
A10: 6 | B10: Rennes | C10: Le meilleur rapport affinité / concentration de l'univers. Pôle cyber de rang national, bassin remarquablement compact (22,3 km d'étendue). | D10: 714 155 hab. · 144 communes · ~7 500 Tle est. · 8 villes ≥ 10 000 hab. | E10: Cyber 5 · Dev 5 · Data/IA 4 · Mkt 4. COMCYBER, DGA-MI, campus cyber breton, b<>com, télécoms. | F10: 87/100, 2e meilleure du panel. | G10: 5/5. | H10: H5 en priorité. Meilleur CONTRE-terrain de H1 du panel. | I10: Écosystème de formation supérieure très fourni (INSA, ENSAI, Rennes 1) : mauvais terrain pour confirmer H1, excellent pour la réfuter. | J10: P1 — retenu au portefeuille : profil cyber le plus pur, à opposer à Vannes.
A11: 7 | B11: Grenoble | C11: Vivier scientifique probablement le plus dense de France rapporté à sa taille, dans un bassin contraint par le relief donc le plus concentré du panel. | D11: 686 820 hab. · 181 communes · ~7 210 Tle est. · 11 villes ≥ 10 000 hab. | E11: Cyber 5 · Dev 5 · Data/IA 5 · Mkt 3. CEA-Leti, STMicroelectronics, instrumentation, calcul. Zone SPÉCIALISÉE, pas généraliste. | F11: 88/100, la meilleure de tout le panel. | G11: 5/5. | H11: H5, H3. Forme avec Rennes une paire de contrôle. | I11: Ne pas y pousser l'offre Marketing Digital sans test préalable : le vivier local paraît mal aligné. Concurrence forte du supérieur public scientifique. | J11: P1 — retenu au portefeuille : seul territoire délibérément spécialisé du cœur.
A12: 8 | B12: Strasbourg | C12: ~8 950 Tle est. avec le profil d'affinité le plus équilibré du panel : 4/5 sur les quatre familles simultanément, cas unique parmi les P1. | D12: 852 523 hab. · 204 communes · 12 villes ≥ 10 000 hab. | E12: Cyber 4 · Dev 4 · Data/IA 4 · Mkt 4. Capitale européenne, banque-assurance, industrie, écosystème numérique structuré. | F12: 67/100. Haguenau nettement excentré (étendue 48,5 km). | G12: 4/5. | H12: H3, H6. Meilleur candidat pour tester l'offre NEXA complète. | I12: Aucune famille n'y est distinctive, ce qui rend l'interprétation des résultats moins tranchée que sur des zones spécialisées. | J12: P1 — non retenu en année 1 pour cette raison d'interprétabilité.
A13: 9 | B13: Montpellier – Nîmes | C13: ~10 080 Tle est. sur l'un des corridors les plus dynamiques démographiquement de France. Bassin interdépartemental par construction (34 + 30). | D13: 960 447 hab. · 136 communes · 12 villes ≥ 10 000 hab. | E13: Cyber 4 · Dev 5 · Data/IA 4 · Mkt 4. IBM, Dell, santé numérique. L'un des rares bassins réellement généralistes. | F13: 45/100, point faible majeur. Étendue 53 km, 33 % de la population à ≤ 20 km. Bassin BICÉPHALE. | G13: 4/5. | H13: H6, et H7 via Nîmes. | I13: Traiter Montpellier et Nîmes comme deux tournées séparées. La concentration est la plus faible du top 10. | J13: P1 — avec scission opérationnelle explicite en deux sous-bassins.
A14: 10 | B14: Angers | C14: Affinité de niveau métropolitain (81/100) sur un vivier de ville moyenne. Capitale French Tech, Cité de l'objet connecté. | D14: 483 174 hab. · 87 communes · ~5 070 Tle est. · 7 villes ≥ 10 000 hab. | E14: Cyber 4 · Dev 5 · Data/IA 4 · Mkt 4. Écosystème électronique / IoT sans équivalent à cette taille de ville. | F14: 72/100, bonne. Étendue 33,9 km. | G14: 4/5, remarquable rapportée à la taille du bassin. | H14: H7 en premier lieu (villes moyennes). | I14: À 88 km de Nantes : une partie du vivier peut viser Nantes en présentiel, y compris chez d'autres écoles. Ce risque de substitution n'est pas mesuré. | J14: P1 — meilleur représentant « haut de gamme » de H7.
A15: 11 | B15: Rouen | C15: Gros vivier (~8 080 Tle est., 6e du panel), bonne concentration (16 villes ≥ 10 000 hab. dans un rayon serré) et profil économique distinct de tous les autres P1. | D15: 769 914 hab. · 336 communes — le maillage le plus fin du panel. | E15: Cyber 4 · Dev 3 · Data/IA 3 · Mkt 3. Chimie, industrie, logistique portuaire, assurance (Matmut). Orienté cybersécurité industrielle et systèmes. | F15: 74/100. | G15: 3/5. Moins visible que Rennes ou Grenoble, mais réelle et industrielle. | H15: H4 — le meilleur terrain du panel. | I15: L'affinité est estimée depuis le tissu industriel, sans donnée DEPP : c'est précisément une zone où le taux réel de STI2D et Bac Pro CIEL doit être vérifié avant d'engager. | J15: P1 — retenu au portefeuille : seul profil industriel non « French Tech » du cœur.
A16: 12 | B16: Clermont-Ferrand | C16: Bassin isolé sans concurrence métropolitaine proche, bien concentré, avec une affinité technique élevée portée par Michelin (data et IA industrielle) et Limagrain. | D16: 529 942 hab. · 208 communes · ~5 560 Tle est. · 9 villes ≥ 10 000 hab. | E16: Cyber 4 · Dev 4 · Data/IA 4 · Mkt 3. | F16: 72/100. 77 % de la population à ≤ 20 km. | G16: 4/5. | H16: H2 — aucune métropole concurrente à moins de 2 h. | I16: Université Clermont Auvergne et offre supérieure locale substantielle : la zone n'est pas sous-dotée, seulement isolée. Bien distinguer les deux dans l'interprétation. | J16: P1.

Sheet Sans pôle étudiant
A1: Zones à vivier réel mais sans offre supérieure locale
A2: Support direct des hypothèses H1 et H2 — celles que NEXA veut pouvoir vérifier, pas confirmer.
A4: Bassin | B4: Priorité | C4: Vivier B1 (Tle est.) | D4: Distance au pôle étudiant majeur (km) | E4: Filières dominantes | F4: Économie numérique (1-5)
A5: Béziers | B5: P3/TEST | C5: 4410 | D5: 59.4 | E5: Marketing | F5: 1
A6: Valence | B6: P3/TEST | C6: 4340 | D6: 70.3 | E6: Cyber+Dev+Data/IA+Marketing | F6: 3
A7: Bayonne | B7: P2 | C7: 3930 | D7: 91.2 | E7: Marketing | F7: 3
A8: Dunkerque | B8: P3/TEST | C8: 3840 | D8: 69.3 | E8: Cyber+Dev+Data/IA+Marketing | F8: 3
A9: Saint-Nazaire | B9: P3/TEST | C9: 3760 | D9: 53.1 | E9: Cyber+Dev+Data/IA+Marketing | F9: 3
A10: Belfort | B10: P2 | C10: 3700 | D10: 38.5 | E10: Cyber+Dev+Data/IA | F10: 3
A11: Vannes | B11: P2 | C11: 3460 | D11: 46.9 | E11: Cyber | F11: 4
A12: Quimper | B12: P3/TEST | C12: 3100 | D12: 52.6 | E12: Dev+Marketing | F12: 2
A13: Évreux | B13: P3/TEST | C13: 3040 | D13: 47.2 | E13: Marketing | F13: 2
A14: Saint-Brieuc | B14: P3/TEST | C14: 2970 | D14: 91.5 | E14: Dev+Marketing | F14: 2
A15: Colmar | B15: P3/TEST | C15: 2970 | D15: 40.1 | E15: Dev+Marketing | F15: 2
A16: Forbach | B16: P3/TEST | C16: 2940 | D16: 52.7 | E16: Marketing | F16: 1
... A22: Angoulême | B22: P3/TEST | C22: 2390 | D22: 89 | E22: Marketing | F22: 3
A24: Lecture
A25: Béziers–Narbonne est le meilleur support de H1/H2 du panel : c'est le plus gros vivier de la liste (~4 410 Terminales estimées, supérieur à Niort et à Vannes), sans aucun pôle étudiant à moins de 59 km, et avec une économie numérique notée 1/5 — il teste donc simultanément H1 et H3.
A26: Saint-Quentin est le contre-test le plus radical (économie numérique 1/5 également), mais son vivier est le plus faible du panel : un résultat nul y serait ambigu.
A27: Attention : « offre locale » est ici approximée par la seule présence d'un pôle étudiant majeur. Le décompte réel des formations numériques post-bac (BTS SIO, BTS CIEL, BUT informatique, BUT MMI, BUT R&T, bachelors) n'a pas pu être collecté — voir ANNEXE C.

Sheet Anomalies
A1: Anomalies territoriales — forte affinité, vivier modeste
A2: Les « pépites » qu'un classement mécanique par volume aurait manquées.
A4: Bassin | B4: Rang | C4: Sous-score affinité /100 | D4: Sous-score vivier /100 | E4: Écart | F4: Pourquoi
A5: Niort | B5: 27 | C5: 87.5 | D5: 1.288539 | E5: =C5-D5 -> 86.211461 | F5: Capitale de la mutualite (MAIF, MACIF, MAAF, Groupama) : besoins IT et data massifs, Niort Tech
A6: Troyes | B6: 38 | C6: 68.75 | D6: 0 | E6: =C6-D6 -> 68.75 | F6: Universite de technologie de Troyes (ingenierie info et cyber), logistique-textile
A7: Angoulême | B7: 42 | C7: 68.75 | D7: 1.288539 | E7: =C7-D7 -> 67.461461 | F7: Pole Magelis : image animee, jeu video, BD - vivier creatif et numerique atypique
A8: Vannes | B8: 19 | C8: 75 | D8: 12.53403 | E8: =C8-D8 -> 62.46597 | F8: Pole cyber breton (Vannes-Ploermel), DGA, Universite Bretagne Sud, ESN
A9: Pau | B9: 18 | C9: 75 | D9: 13.299417 | E9: =C9-D9 -> 61.700583 | F9: TotalEnergies et supercalculateur Pangea : l'un des plus gros centres de calcul prives d'Europe
A10: Besançon | B10: 36 | C10: 68.75 | D10: 8.2592079 | E10: =C10-D10 -> 60.490792 | F10: Microtechniques, FEMTO-ST, biomedical : culture technique tres marquee
A11: Poitiers | B11: 35 | C11: 68.75 | D11: 10.08335 | E11: =C11-D11 -> 58.66665 | F11: Futuroscope (image-numerique), laboratoire informatique universitaire, mutuelles proches
A12: Lorient | B12: 33 | C12: 62.5 | D12: 7.5352301 | E12: =C12-D12 -> 54.96477 | F12: Naval Group, cyberdefense navale, Universite Bretagne Sud, pole mer
A13: Angers | B13: 10 | C13: 81.25 | D13: 26.550701 | E13: =C13-D13 -> 54.699299 | F13: Capitale French Tech, Cite de l'objet connecte, electronique-IoT, Thales
A14: Brest | B14: 15 | C14: 75 | D14: 22.723809 | E14: =C14-D14 -> 52.276191 | F14: Capitale French Tech Brest Bretagne Ouest ; cyberdefense navale, Naval Group, Thales, IMT Atlantique
A15: Bayonne | B15: 25 | C15: 68.75 | D15: 16.912564 | E15: =C15-D15 -> 51.837436 | F15: French Tech Pays Basque ; economie de marque, tourisme, sport-glisse = vivier marketing fort
A16: La Rochelle | B16: 37 | C16: 68.75 | D16: 17.541779 | E16: =C16-D16 -> 51.208221 | F16: Ecosysteme French Tech, universite, port ; territoire pilote sur la donnee environnementale

Sheet Hypothèses H1-H8
A1: Les 8 hypothèses expérimentales et leur terrain de test
A2: Aucune de ces variables n'entre dans le score. Elles sont collectées pour être confrontées aux résultats commerciaux réels de l'année 1.
A4: # | B4: Hypothèse | C4: Terrain de test dans le panel | D4: Zone(s) retenue(s) au portefeuille | E4: Testable en l'état ?
A5: H1 | B5: Les zones faiblement couvertes en formations numériques convertissent mieux. | C5: Paires appariées par vivier ET par région : Lorient/Saint-Brieuc (écart 0,3 %), Amiens/Dunkerque (1,6 %), La Rochelle/Bayonne (1,8 %), Perpignan/Béziers (6,6 %). Contre-terrain : Rennes et Grenoble, offre locale maximale. | D5: Vannes, Béziers–Narbonne (porteuses) · Rennes, Grenoble (contre-test) | E5: Partiellement — « offre locale » approximée par la seule présence d'un pôle étudiant. Le décompte des formations numériques post-bac reste à collecter.
A6: H2 | B6: L'éloignement des grands pôles étudiants augmente l'intérêt pour le campus À distance. | C6: Gradient complet : 0 km (Rouen, Dijon, Caen, Grenoble) → 38 km (Belfort) → 47 km (Vannes, Évreux) → 59 km (Béziers) → 69 km (Dunkerque) → 92 km (Saint-Brieuc) → 1 415 km (Mayotte) → La Réunion. | D6: Vannes, Béziers · La Réunion sur modalité distincte | E6: Oui — variable observée et publiée (colonne Y de l'onglet « 59 bassins »).
A7: H3 | B7: Un environnement économique numérique dynamique augmente l'intérêt pour les formations NEXA. | C7: Gradient 5/5 (Marseille, Toulouse, Bordeaux, Nantes, Rennes, Grenoble, Nice) → 3/5 (Rouen, Valence, Dijon, Dunkerque) → 1/5 (Béziers, Forbach, Saint-Quentin, Mamoudzou). | D7: Béziers–Narbonne (contre-test décisif) · Marseille, Toulouse (haut du gradient) | E7: Oui, mais l'axe économie est une estimation experte, non une mesure d'emploi numérique.
A8: H4 | B8: L'économie numérique influence davantage l'alternance que le recrutement étudiant. | C8: Zones à besoins IT industriels réels mais écosystème start-up modeste : Rouen, Le Havre, Belfort–Montbéliard, Dunkerque, Saint-Nazaire — opposées à Grenoble, Rennes, Marseille. | D8: Rouen | E8: Oui, à condition de suivre SÉPARÉMENT le taux d'inscription B1 et le taux de signature en alternance.
A9: H5 | B9: Les territoires concentrant NSI / STI2D / CIEL surperforment en Cyber/Dev. | C9: Rennes, Grenoble, Toulouse, Marseille, Belfort, Vannes, Brest, Toulon. | D9: Rennes, Grenoble, Toulouse, Vannes | E9: NON en l'état. Les notes cyber/dev sont déduites du tissu économique, pas des effectifs de spécialités. Prérequis absolu : lancer pipeline/05_enrichissement_depp.py.
A10: H6 | B10: Les territoires à forte présence STMG ou généraliste performent en Marketing Digital. | C10: Gros vivier : Bordeaux (5/5), Nantes (5/5). Vivier moyen : Bayonne (5/5), Angoulême (5/5), Perpignan, Béziers, Avignon, Reims, Tours, Orléans. | D10: Bordeaux, Béziers–Narbonne | E10: Partiellement — la présence effective de STMG est inférée depuis l'économie tertiaire locale, pas mesurée.
A11: H7 | B11: Les villes moyennes constituent un marché particulièrement intéressant. | C11: Cinq bassins ajoutés SOUS le seuil de population pour rendre l'hypothèse testable : Troyes, Angoulême, Niort, Albi, Saint-Malo. Comparés à Angers (ville moyenne « haut de gamme ») et aux métropoles P1. | D11: Niort · Angers en appui | E11: Oui. Indicateur clé : rendement par IE (inscriptions / IE réalisée), pas volume absolu.
A12: H8 | B12: Les territoires disposant d'un Campus connecté présentent une meilleure réceptivité au modèle À distance. | C12: 89 lieux labellisés au niveau national. Deux implantations seulement confirmées par recherche documentaire (Cahors, Nevers — vague expérimentale 2019), aucune dans un bassin retenu. | D12: — (à déterminer après collecte) | E12: NON en l'état. La liste DGESIP n'a pas pu être récupérée (accès bloqué). Collecte de quelques heures à mener avant le lancement.
A14: Ce qu'il faut instrumenter pour que tout ceci serve
A15: Sans suivi du funnel PAR ZONE, aucune de ces hypothèses ne sera vérifiable en fin d'année. Le minimum : zone → lycées prospectés → IE obtenues → lycéens exposés → leads → candidatures → admissions → inscriptions B1.
A16: Trois ratios suffisent à trancher la plupart des hypothèses : (1) taux d'obtention d'IE = IE obtenues / lycées prospectés — mesure l'accessibilité commerciale, pas le potentiel ; (2) taux de captation = leads / lycéens exposés — indicateur central pour H1, H2, H3, H8 ; (3) rendement par IE = inscriptions / IE réalisée — seul indicateur permettant de comparer une ville moyenne à une métropole (H7).
A17: RECOMMANDATION : créer un champ « bassin d'opportunité » sur l'objet lycée du CRM et l'alimenter depuis data/handoff_etape2.json AVANT la première IE. Sans lui, l'année 1 produira des inscriptions mais aucun modèle exploitable pour l'année 2.

Sheet Exclusion 60 km
A1: Périmètre d'exclusion des campus physiques — 60 km autour de Paris, Lyon et Lille
A2: Calcul commune par commune (distance orthodromique). Aucun département n'est exclu en bloc.
A4: Dép. | B4: Département | C4: Nb communes | D4: Communes exclues | E4: % communes exclues | F4: % population exclue | G4: Statut
A5: 01 | B5: Ain | C5: 391 | D5: 182 | E5: 0.465 | F5: 0.52 | G5: partiellement exclu - reste exploitable
A6: 07 | B6: Ardèche | C6: 335 | D6: 26 | E6: 0.078 | F6: 0.142 | G6: partiellement exclu - reste exploitable
A7: 26 | B7: Drôme | C7: 362 | D7: 13 | E7: 0.036 | F7: 0.047 | G7: partiellement exclu - reste exploitable
A8: 28 | B8: Eure-et-Loir | C8: 363 | D8: 2 | E8: 0.006 | F8: 0.016 | G8: partiellement exclu - reste exploitable
A9: 38 | B9: Isère | C9: 512 | D9: 208 | E9: 0.406 | F9: 0.376 | G9: partiellement exclu - reste exploitable
A10: 42 | B10: Loire | C10: 320 | D10: 169 | E10: 0.528 | F10: 0.727 | G10: majoritairement exclu
A11: 59 | B11: Nord | C11: 647 | D11: 435 | E11: 0.672 | F11: 0.822 | G11: majoritairement exclu
A12: 60 | B12: Oise | C12: 680 | D12: 246 | E12: 0.362 | F12: 0.543 | G12: partiellement exclu - reste exploitable
A13: 62 | B13: Pas-de-Calais | C13: 887 | D13: 406 | E13: 0.458 | F13: 0.626 | G13: partiellement exclu - reste exploitable
A14: 69 | B14: Rhône | C14: 266 | D14: 260 | E14: 0.977 | F14: 0.999 | G14: majoritairement exclu
A15: 71 | B15: Saône-et-Loire | C15: 563 | D15: 12 | E15: 0.021 | F15: 0.025 | G15: partiellement exclu - reste exploitable
A16: 75 | B16: Paris | C16: 1 | D16: 1 | E16: 1 | F16: 1 | G16: totalement exclu
... A23: 95 | B23: Val-d'Oise | C23: 183 | D23: 180 | E23: 0.984 | F23: 0.999 | G23: majoritairement exclu
B25: TOTAL France | C25: =SUM(C5:C23) -> 6592 | D25: =SUM(D5:D23) -> 2982
A27: Deux conséquences commercialement importantes
A28: ① Sortent du champ du campus À distance : Saint-Étienne (≈ 51 km de Lyon), Valenciennes, Arras, Douai, Béthune (< 60 km de Lille), Beauvais, Creil, Compiègne et Melun (< 60 km de Paris). Ce sont des « villes moyennes » souvent citées spontanément — la règle des 60 km les neutralise.
A29: ② L'Isère reste exploitable à 59 % : Grenoble est à 94 km de Lyon et demeure pleinement dans le périmètre. De même une large moitié du Pas-de-Calais (Boulogne, Calais, Montreuil) reste ouverte.
A30: Le total ci-dessus ne porte que sur les 19 départements touchés. À l'échelle nationale : 2 982 communes exclues sur 34 863, soit 19,1 M habitants (28,0 % de la population française).

Sheet ANNEXE A — Démarche
A1: ANNEXE A — La démarche, étape par étape
A2: Ce qui a été fait, dans quel ordre, et pourquoi.
A4: Le principe directeur
A5: La mission ne demandait pas le territoire théoriquement parfait pour le distanciel, mais les territoires disposant d'assez de potentiel étudiant compatible NEXA pour justifier une expérimentation IE, avec une concentration géographique permettant une activation commerciale réaliste. L'année 1 doit produire des inscriptions ET produire de l'apprentissage. La sélection est donc assez rigoureuse pour éviter une prospection nationale indifférenciée, assez ouverte pour ne pas enfermer NEXA dans ses propres hypothèses de départ.
A7: Étape 1 — Exclure les zones de campus physiques (règle des 60 km)
A8: Référentiel : 34 863 communes géolocalisées, couvrant 68,3 M habitants (population légale INSEE via Etalab, coordonnées La Poste). Distance orthodromique (formule de haversine, rayon terrestre 6 371,0088 km) entre le chef-lieu de chaque commune et chacun des trois campus. Une commune est exclue si la distance minimale est ≤ 60 km.
A9: Point de méthode important : le calcul est fait COMMUNE PAR COMMUNE. Aucun département n'a été exclu en bloc parce qu'il contient un campus. Résultat : 2 982 communes exclues (19,1 M hab., 28,0 % de la population), 4 départements totalement exclus, 11 départements partiellement touchés qui restent exploitables.
A10: Coordonnées retenues — Paris : 44bis quai de Jemmapes 75010 (48,8709 / 2,3646) · Lille : 250 rue Madeleine Rebérioux 59000 (50,6216 / 3,0790) · Lyon : centre-ville, secteur Bellecour (45,7578 / 4,8320). L'adresse exacte du campus lyonnais n'a pas été trouvée en source primaire ; à 60 km de rayon, une imprécision de 2 km est sans effet matériel.
A12: Étape 2 — Construire les bassins SANS partir du découpage administratif
A13: L'unité commerciale recherchée est le bassin d'activation IE, pas le département. La construction est algorithmique, pas déclarative :
A14: ① Villes-centres candidates : communes de ≥ 15 000 hab., hors exclusion, qui sont un MAXIMUM LOCAL de population dans un rayon de 12 km. Ce filtre évite qu'un bassin soit centré sur une banlieue — sans lui, l'algorithme centrait le bassin bordelais sur Le Bouscat et le bassin nantais sur Bouguenais. 377 candidates → 231 maxima locaux.
A15: ② Rayon de bassin : 30 km autour de la ville-centre, soit ~45 min de trajet — l'amplitude réaliste d'une tournée IE dans la journée.
... A38: Le coût de déplacement n'intervient dans aucun de ces trois principes. Il agit uniquement sur le NOMBRE de zones testées (9 sur 59), pas sur leur identité. L'intégrer à la sélection reviendrait à confondre « où le potentiel est-il réel ? » avec « où est-il commode d'aller ? », et concentrerait mécaniquement l'expérimentation autour de l'Île-de-France, de Rhône-Alpes et des Hauts-de-France.

Sheet ANNEXE B — Choix de méthode
A1: ANNEXE B — Pourquoi ces choix de méthode
A2: Les décisions structurantes et ce qu'elles écartent.
A4: Pourquoi ne pas commencer par les lycées ?
A5: Produire d'emblée une liste de 1 000 ou 2 000 établissements aurait donné un fichier commercial sans stratégie. La logique appliquée est : où sont les viviers ? → où sont-ils assez intéressants ET assez concentrés pour justifier une expérimentation ? → quels bassins retenir ? Les établissements précis relèvent de l'étape 2, une fois les zones validées. Ce classeur reste donc strictement territorial.
A7: Pourquoi des bassins et pas des départements ?
A8: Un département est une unité administrative, pas un marché. La Haute-Garonne et le Gers n'ont pas le même sens commercial que « Toulouse et sa couronne ». Les bassins construits ici correspondent à ce qu'une équipe commerciale peut réellement travailler dans une journée, et plusieurs d'entre eux sont interdépartementaux parce que la géographie économique l'impose.
A10: Pourquoi la « propension au distanciel » est-elle exclue du score ?
A11: C'est la décision méthodologique la plus importante du livrable, et elle est délibérée. Nous ne savons pas encore si l'éloignement d'une université, la ruralité, l'IPS, l'absence d'école numérique ou la présence d'un Campus connecté prédisent réellement l'intérêt pour NEXA À distance. Les intégrer au scoring maintenant reviendrait à sélectionner uniquement les territoires qui confirment nos hypothèses de départ — et à sortir de l'année 1 avec un modèle qui n'aurait fait que se refléter lui-même.
A12: Ces variables sont donc COLLECTÉES mais NON SCORÉES : ce sont des variables expérimentales, destinées à être confrontées aux résultats commerciaux réels. Si l'hypothèse se confirme, elle pourra fonder la stratégie commerciale du campus À distance en année 2.
A13: Conséquence assumée, et c'est l'enseignement méthodologique central de cette étape : les 12 zones P1 contiennent TOUTES un pôle étudiant majeur. Le score, ne récompensant que le volume, l'affinité, la concentration et l'économie, désigne mécaniquement des territoires bien dotés en enseignement supérieur — c'est-à-dire exactement l'inverse de l'intuition du « territoire idéal pour le distanciel ». Cette tension justifie à elle seule que le portefeuille de test ne soit pas constitué des seuls P1.
A15: Pourquoi la racine carrée sur le vivier ?
A16: Un classement mécanique par volume ferait remonter les plus grandes agglomérations françaises et rien d'autre. La normalisation en racine carrée atténue ce biais sans l'effacer — le volume reste un avantage réel, mais décroissant. C'est ce qui permet à Angers (5 070 Tle est.) de se classer devant Metz (7 230) grâce à son affinité et à sa concentration.
... A28: Parce qu'un plan composé des seules meilleures zones ne peut rien réfuter. Béziers–Narbonne a un vivier réel (~4 410 Tle est., supérieur à Niort et Vannes), une économie numérique notée 1/5, et aucun pôle étudiant à moins de 59 km. Si Béziers convertit, l'axe économie numérique devra être fortement dépondéré en année 2 et l'hypothèse d'un potentiel porté par le seul vivier scolaire prendra le dessus. Si Béziers ne convertit pas, le modèle actuel est conforté. Dans les deux cas, NEXA apprend quelque chose — ce qui n'est pas garanti en ne testant que des zones favorables.

Sheet ANNEXE C — Limites
A1: ANNEXE C — Ce que ce livrable ne permet PAS d'affirmer
A2: À lire avant d'engager le moindre budget.
A4: La contrainte de collecte, à l'origine de la plupart des limites
A5: L'environnement de production disposait d'un accès réseau restreint. data.education.gouv.fr (API DEPP), data.gouv.fr, enseignementsup-recherche.gouv.fr, ONISEP, Parcoursup et les API INSEE étaient TOUS bloqués. Seuls le référentiel Etalab (via npm), la base des codes postaux La Poste (via GitHub) et la recherche web étaient accessibles.
A6: Il en découle que l'ossature géographique et démographique de l'analyse est observée et recalculable, mais que son ossature SCOLAIRE est un proxy. Aucune valeur n'a été inventée pour combler un trou : les colonnes non collectées sont marquées « À COLLECTER » et jamais remplies par zéro.
A8: ① Le vivier n'est pas mesuré
A9: Toutes les valeurs de vivier sont issues de population × 1,05 %. Ce ratio national ignore : la structure par âge locale (La Réunion et Mayotte sont nettement plus jeunes — leur vivier est probablement SOUS-estimé ; Béziers, Perpignan et Saint-Malo, plus âgés, probablement SUR-estimés) ; l'attractivité scolaire d'une ville-centre sur sa périphérie ; le poids de l'enseignement privé, très variable selon les régions ; les taux de scolarisation et de redoublement locaux.
A10: CONSÉQUENCE PRATIQUE : ces chiffres servent à CLASSER des bassins entre eux, pas à dimensionner une campagne. Ne pas les reprendre dans un budget ou un objectif commercial.
A12: ② L'affinité par filière n'est pas une donnée scolaire
A13: Les notes cyber / dev / data / marketing sont dérivées du tissu économique. Elles reposent sur une chaîne de raisonnement plausible mais NON VÉRIFIÉE : économie industrielle locale → lycées techniques → présence de STI2D et Bac Pro CIEL → vivier cyber/dev. Chaque maillon peut être faux.
A14: Deux faits nationaux invitent à la prudence : un lycée sur trois ne propose toujours pas la spécialité NSI ; et NSI ne représente que 4,0 % des élèves de Terminale générale en 2025 (4,5 % en 2024, en baisse). Autrement dit, le vivier « NSI » d'un bassin de 5 000 Terminales générales se compte en quelques CENTAINES d'élèves, très inégalement répartis. Un territoire industriel peut parfaitement n'offrir NSI que dans deux lycées.
A15: CONSÉQUENCE PRATIQUE : l'axe affinité (25 % du score) doit être remplacé par des données DEPP AVANT l'allocation du budget de déplacement.
... A35: Les points 1, 2, 3 et 6 sont couverts par le script pipeline/05_enrichissement_depp.py, fourni dans le dépôt et qui n'a pas pu être exécuté faute d'accès réseau.

Sheet ANNEXE D — Sources
A1: ANNEXE D — Sources, millésimes et niveaux de confiance
A2: Traçabilité des données utilisées.
A4: Source | B4: Millésime | C4: Usage dans l'analyse | D4: Accès / date de collecte
A5: INSEE / Etalab — @etalab/decoupage-administratif v6.0.0 | B5: population légale en vigueur 2026 | C5: Population, département, région, EPCI de 34 863 communes | D5: npm — 15/08/2026
A6: La Poste — base officielle des codes postaux (miroir high54/Communes-France-JSON) | B6: 2025 | C6: Coordonnées GPS par code INSEE | D6: GitHub — 15/08/2026
A7: IGN / Etalab — gregoiredavid/france-geojson | B7: 2024 | C7: Contours départementaux (contrôle) | D7: GitHub — 15/08/2026
A8: DEPP — RERS 2025 | B8: rentrée 2024 | C8: ~1,597 M élèves en formations générales et technologiques (lycée) | D8: recherche documentaire — 15/08/2026
A9: DEPP | B9: rentrée 2024 | C9: ~651 000 élèves en voie professionnelle (lycée, hors apprentis) | D9: recherche documentaire — 15/08/2026
A10: DEPP | B10: rentrée 2025 | C10: 5,621 M élèves du second degré, tous niveaux | D10: recherche documentaire — 15/08/2026
A11: DEPP — note d'information Enseignements de spécialités | B11: 2025 | C11: Part de NSI en Terminale générale : 4,0 % (4,5 % en 2024) | D11: recherche documentaire — 15/08/2026
A12: DEPP | B12: 2024 | C12: Part des filles en NSI Terminale : 13,7 % | D12: recherche documentaire — 15/08/2026
A13: Société informatique de France | B13: 2024 | C13: ~1 lycée sur 3 ne propose pas NSI | D13: recherche documentaire — 15/08/2026
A14: DEPP | B14: rentrée 2024 | C14: Part de la voie générale en Terminale GT : 72,4 % | D14: recherche documentaire — 15/08/2026
A15: MESR / DGESIP | B15: 2024-2025 | C15: 87 à 89 lieux labellisés Campus connecté (liste complète NON récupérée) | D15: recherche documentaire — 15/08/2026
... A17: NEXA Digital School | B17: 2026 | C17: Campus physiques : Paris, Lyon, Lille — liste confirmée par NEXA | D17: nexa.fr — 15/08/2026
A20: Indicateur | B20: Niveau de confiance | C20: Motif
A21: Exclusion des 60 km | B21: ÉLEVÉE | C21: Calcul déterministe sur référentiel officiel
A22: Population, communes, départements, régions | B22: ÉLEVÉE | C22: INSEE / Etalab
A23: Distances, étendue, concentration | B23: ÉLEVÉE | C23: Calcul, sous réserve orthodromique vs routier
A24: Composition des bassins | B24: ÉLEVÉE | C24: Algorithme reproductible et documenté
A25: Vivier B1 (Terminales estimées) | B25: MOYENNE | C25: Proxy national, ignore la structure d'âge locale
A26: Notes cyber / dev / data / marketing | B26: FAIBLE | C26: Estimation experte, non issue de données scolaires
A27: Note économie numérique | B27: MOYENNE | C27: Ancrée sur des faits vérifiables, mais non quantifiée
A28: Score global | B28: MOYENNE | C28: 20 % seulement entièrement observés
A29: Classement P1 / P2 / P3 | B29: MOYENNE | C29: À réviser après enrichissement DEPP
A30: Portefeuille de test recommandé | B30: MOYENNE | C30: Combine le score et un objectif de diversité de profils et d'hypothèses
A32: En une phrase : la géographie de ce livrable est solide, sa démographie est raisonnable, sa dimension scolaire reste à établir.

Sheet Légende
A1: Légende — nature de chaque donnée
A2: Distinguer ce qui est observé de ce qui est estimé est essentiel pour interpréter ce classeur.
A4: Nature | B4: Ce que cela signifie | C4: Colonnes concernées
A5: DONNÉE OBSERVÉE | B5: Mesure issue d'une source officielle, recalculable à l'identique. | C5: Population, nb communes, départements, régions, villes principales, étendue, concentration à 20 km, distances, exclusion 60 km
A6: PROXY | B6: Grandeur non disponible, remplacée par une approximation documentée et justifiée. | C6: Vivier B1 — Terminales estimées (population × 1,05 %)
A7: ESTIMATION EXPERTE | B7: Jugement analytique fondé sur des faits documentés, mais qui n'est PAS une mesure. | C7: Cyber, Dev, Data/IA, Marketing, Économie numérique (notes de 1 à 5)
A8: HYPOTHÈSE | B8: Choix de modélisation susceptible d'être révisé par les résultats de l'année 1. | C8: Pondérations du score (40/25/20/15), table d'affinité série → filière
A9: INTERPRÉTATION | B9: Lecture stratégique construite à partir des éléments ci-dessus. | C9: Colonne « Pourquoi », priorités P1/P2/P3, portefeuille de test recommandé
A12: Règle absolue appliquée dans tout le livrable
A13: Une absence de donnée n'est JAMAIS transformée en zéro. Les grandeurs non collectées sont marquées « À COLLECTER » avec leur source, et jamais estimées silencieusement.
A15: Contenu des onglets
A16: Paramètres — les 4 pondérations du score, modifiables (cellules jaunes). La colonne SCORE de l'onglet « 59 bassins » se recalcule automatiquement.
A17: Synthèse — chiffres clés et recommandation en une page.
A18: Portefeuille test — les 9 zones recommandées pour l'année 1, avec leur rôle et l'hypothèse testée.
A19: 59 bassins — l'univers complet avec tous les indicateurs. Filtres activés, volets figés.
A20: Fiches P1 — lecture stratégique détaillée des 12 zones prioritaires.
A21: Sans pôle étudiant — les 18 zones à vivier réel mais sans université de plein exercice (support de H1 et H2).
A22: Anomalies — les territoires dont l'affinité dépasse le plus largement le poids démographique.
A23: Hypothèses H1-H8 — le plan d'apprentissage de l'année 1 et ce qui est testable en l'état.
A24: Exclusion 60 km — le périmètre neutralisé, département par département.
... A31: L'étape 2 reçoit chaque zone retenue sous forme de périmètre géométrique (point central + rayon de 30 km) via le fichier data/handoff_etape2.json du dépôt, et recherche exhaustivement les établissements de ce périmètre avant de les classer P1/P2/P3. Ce classeur ne descend volontairement pas au niveau lycée.
